README.md
pyproject.toml
setup.py
puzzle_radicale_auth_ldap/__init__.py
puzzle_radicale_auth_ldap/ldap3imports.py
puzzle_radicale_auth_ldap.egg-info/PKG-INFO
puzzle_radicale_auth_ldap.egg-info/SOURCES.txt
puzzle_radicale_auth_ldap.egg-info/dependency_links.txt
puzzle_radicale_auth_ldap.egg-info/requires.txt
puzzle_radicale_auth_ldap.egg-info/top_level.txt